[
    {
        "key": "dbln",
        "value": "%7B%2261577692216296%22%3A%22M9naEXBQ%22%2C%2261577724456610%22%3A%22u3AVxxPi%22%7D",
        "domain": "facebook.com",
        "path": "/login/device-based/",
        "hostOnly": false,
        "creation": "2025-09-19T09:59:48.041Z",
        "lastAccessed": "2025-09-19T09:59:48.042Z"
    },
    {
        "key": "datr",
        "value": "MtHLaOb6d3aeUy7iePxCAZPV",
        "domain": "facebook.com",
        "path": "/",
        "hostOnly": false,
        "creation": "2025-09-19T09:59:48.042Z",
        "lastAccessed": "2025-09-19T09:59:48.042Z"
    },
    {
        "key": "sb",
        "value": "MtHLaI6lv1m_oUyTVtPzRESE",
        "domain": "facebook.com",
        "path": "/",
        "hostOnly": false,
        "creation": "2025-09-19T09:59:48.042Z",
        "lastAccessed": "2025-09-19T09:59:48.042Z"
    },
    {
        "key": "ps_l",
        "value": "1",
        "domain": "facebook.com",
        "path": "/",
        "hostOnly": false,
        "creation": "2025-09-19T09:59:48.042Z",
        "lastAccessed": "2025-09-19T09:59:48.042Z"
    },
    {
        "key": "ps_n",
        "value": "1",
        "domain": "facebook.com",
        "path": "/",
        "hostOnly": false,
        "creation": "2025-09-19T09:59:48.042Z",
        "lastAccessed": "2025-09-19T09:59:48.042Z"
    },
    {
        "key": "locale",
        "value": "en_US",
        "domain": "facebook.com",
        "path": "/",
        "hostOnly": false,
        "creation": "2025-09-19T09:59:48.042Z",
        "lastAccessed": "2025-09-19T09:59:48.042Z"
    },
    {
        "key": "vpd",
        "value": "v1%3B646x360x2",
        "domain": "facebook.com",
        "path": "/",
        "hostOnly": false,
        "creation": "2025-09-19T09:59:48.042Z",
        "lastAccessed": "2025-09-19T09:59:48.042Z"
    },
    {
        "key": "pas",
        "value": "61577692216296%3A80zMrHEYLy%2C61577724456610%3AUgBm6ujCTv",
        "domain": "facebook.com",
        "path": "/",
        "hostOnly": false,
        "creation": "2025-09-19T09:59:48.042Z",
        "lastAccessed": "2025-09-19T09:59:48.042Z"
    },
    {
        "key": "m_pixel_ratio",
        "value": "2",
        "domain": "facebook.com",
        "path": "/",
        "hostOnly": false,
        "creation": "2025-09-19T09:59:48.042Z",
        "lastAccessed": "2025-09-19T09:59:48.042Z"
    },
    {
        "key": "wd",
        "value": "360x800",
        "domain": "facebook.com",
        "path": "/",
        "hostOnly": false,
        "creation": "2025-09-19T09:59:48.042Z",
        "lastAccessed": "2025-09-19T09:59:48.042Z"
    },
    {
        "key": "c_user",
        "value": "61577724456610",
        "domain": "facebook.com",
        "path": "/",
        "hostOnly": false,
        "creation": "2025-09-19T09:59:48.042Z",
        "lastAccessed": "2025-09-19T09:59:48.042Z"
    },
    {
        "key": "xs",
        "value": "15%3AdQXsRlCN_ASTgQ%3A2%3A1758275366%3A-1%3A-1",
        "domain": "facebook.com",
        "path": "/",
        "hostOnly": false,
        "creation": "2025-09-19T09:59:48.042Z",
        "lastAccessed": "2025-09-19T09:59:48.042Z"
    },
    {
        "key": "fr",
        "value": "0OyQr6hQHgN2TJhGQ.AWcBN1BdhEXwInalSHeWxLvDW92Go4x0W9j535p68SbSWAXfyvU.Boy9Ey..AAA.0.0.BozScp.AWexxuiUx2lfzVTcxXIVwZW7dBU",
        "domain": "facebook.com",
        "path": "/",
        "hostOnly": false,
        "creation": "2025-09-19T09:59:48.042Z",
        "lastAccessed": "2025-09-19T09:59:48.042Z"
    },
    {
        "key": "wl_cbv",
        "value": "v2%3Bclient_version%3A2927%3Btimestamp%3A1758275369",
        "domain": "facebook.com",
        "path": "/",
        "hostOnly": false,
        "creation": "2025-09-19T09:59:48.042Z",
        "lastAccessed": "2025-09-19T09:59:48.042Z"
    },
    {
        "key": "fbl_st",
        "value": "100629720%3BT%3A29304590",
        "domain": "facebook.com",
        "path": "/",
        "hostOnly": false,
        "creation": "2025-09-19T09:59:48.042Z",
        "lastAccessed": "2025-09-19T09:59:48.042Z"
    }
]
